Workbook

Sheet Data
A1: Customer ID | B1: Gender | C1: Product_Category | D1: Customer_Segment | E1: Payment_Method | F1: Region | G1: City | H1: Sales_Channel | I1: Order_Status | J1: Sales | K1: Quantity Sold | L1: Discount Rate | M1: Delivery_Days | N1: Profit Margin
A2: 1 | B2: Male | C2: Sports & Outdoors | D2: Business | E2: Cash | F2: South | G2: Philadelphia | H2: Online | I2: Pending | J2: 619.41734 | K2: 36.148044 | L2: 0.16617446 | M2: 4.5019279 | N2: 0.28936177
A3: 2 | B3: Female | C3: Clothing | D3: Wholesale | E3: Cash | F3: West | G3: Phoenix | H3: Catalog | I3: Cancelled | J3: 886.13398 | K3: 22.670661 | L3: 0.099897857 | M3: 2.2397971 | N3: 0.220737
A4: 3 | B4: Male | C4: Clothing | D4: Wholesale | E4: Credit Card | F4: South | G4: Philadelphia | H4: In-store | I4: Returned | J4: 449.13093 | K4: 25.659829 | L4: 0.099897857 | M4: 2.1554926 | N4: 0.25439927
A5: 4 | B5: Female | C5: Beauty & Health | D5: Business | E5: Credit Card | F5: East | G5: San Diego | H5: Catalog | I5: Cancelled | J5: 610.02358 | K5: 22.712923 | L5: 0.18491416 | M5: 4.7441648 | N5: 0.30629011
A6: 5 | B6: Male | C6: Beauty & Health | D6: Wholesale | E6: PayPal | F6: East | G6: Dallas | H6: Online | I6: Returned | J6: 364.77613 | K6: 22.179177 | L6: 0.07300551 | M6: 2.7507158 | N6: 0.21021883
A7: 6 | B7: Female | C7: Home & Kitchen | D7: Business | E7: Cash | F7: East | G7: Chicago | H7: Online | I7: Completed | J7: 576.61392 | K7: 32.112951 | L7: 0.17917733 | M7: 4.5020717 | N7: 0.2921224
A8: 7 | B8: Male | C8: Sports & Outdoors | D8: Business | E8: Cash | F8: North | G8: Los Angeles | H8: Online | I8: Cancelled | J8: 449.13093 | K8: 34.16821 | L8: 0.22561918 | M8: 5.4069273 | N8: 0.31072854
A9: 8 | B9: Female | C9: Home & Kitchen | D9: Wholesale | E9: PayPal | F9: East | G9: San Diego | H9: Online | I9: Cancelled | J9: 372.90517 | K9: 32.509504 | L9: 0.099897857 | M9: 2.1554926 | N9: 0.21104944
A10: 9 | B10: Male | C10: Home & Kitchen | D10: Wholesale | E10: Bank Transfer | F10: North | G10: San Diego | H10: Online | I10: Cancelled | J10: 545.77267 | K10: 28.966599 | L10: 0.18491416 | M10: 4.0998691 | N10: 0.27918052
A11: 10 | B11: Female | C11: Clothing | D11: Individual | E11: Bank Transfer | F11: North | G11: Phoenix | H11: Catalog | I11: Returned | J11: 413.90525 | K11: 22.800457 | L11: 0.099897857 | M11: 2.391061 | N11: 0.22284298
A12: 11 | B12: Male | C12: Sports & Outdoors | D12: Wholesale | E12: Cash | F12: East | G12: New York | H12: Catalog | I12: Returned | J12: 600.05115 | K12: 37.920199 | L12: 0.18251118 | M12: 4.4498966 | N12: 0.29895453
A13: 12 | B13: Female | C13: Electronics | D13: Wholesale | E13: Cash | F13: West | G13: Chicago | H13: Phone | I13: Completed | J13: 726.81694 | K13: 34.16821 | L13: 0.25577788 | M13: 7.2391498 | N13: 0.3515502
... A101: 100 | B101: Female | C101: Home & Kitchen | D101: Business | E101: Cash | F101: West | G101: Houston | H101: In-store | I101: Cancelled | J101: 419.38043 | K101: 36.139059 | L101: 0.099897857 | M101: 2.6042442 | N101: 0.23183288

Sheet Reg
A1: =Data!L1 -> Discount Rate | B1: =Data!M1 -> Delivery_Days | C1: =Data!N1 -> Profit Margin | E1: Question
A2: =Data!L2 -> 0.16617446 | B2: =Data!M2 -> 4.5019279 | C2: =Data!N2 -> 0.28936177 | E2: Is there any significant influence of discount rate and delivery days on profit margin?
A3: =Data!L3 -> 0.099897857 | B3: =Data!M3 -> 2.2397971 | C3: =Data!N3 -> 0.220737
A4: =Data!L4 -> 0.099897857 | B4: =Data!M4 -> 2.1554926 | C4: =Data!N4 -> 0.25439927
A5: =Data!L5 -> 0.18491416 | B5: =Data!M5 -> 4.7441648 | C5: =Data!N5 -> 0.30629011
A6: =Data!L6 -> 0.07300551 | B6: =Data!M6 -> 2.7507158 | C6: =Data!N6 -> 0.21021883
A7: =Data!L7 -> 0.17917733 | B7: =Data!M7 -> 4.5020717 | C7: =Data!N7 -> 0.2921224
A8: =Data!L8 -> 0.22561918 | B8: =Data!M8 -> 5.4069273 | C8: =Data!N8 -> 0.31072854
A9: =Data!L9 -> 0.099897857 | B9: =Data!M9 -> 2.1554926 | C9: =Data!N9 -> 0.21104944
A10: =Data!L10 -> 0.18491416 | B10: =Data!M10 -> 4.0998691 | C10: =Data!N10 -> 0.27918052
A11: =Data!L11 -> 0.099897857 | B11: =Data!M11 -> 2.391061 | C11: =Data!N11 -> 0.22284298
A12: =Data!L12 -> 0.18251118 | B12: =Data!M12 -> 4.4498966 | C12: =Data!N12 -> 0.29895453
A13: =Data!L13 -> 0.25577788 | B13: =Data!M13 -> 7.2391498 | C13: =Data!N13 -> 0.3515502
A14: =Data!L14 -> 0.17917733 | B14: =Data!M14 -> 2.2344005 | C14: =Data!N14 -> 0.25465479
... A101: =Data!L101 -> 0.099897857 | B101: =Data!M101 -> 2.6042442 | C101: =Data!N101 -> 0.23183288
